plotnine3d/__init__.py
plotnine3d/geoms.py
plotnine3d/plot.py
plotnine3d/py.typed
plotnine3d-0.0.1.dist-info/LICENSE
plotnine3d-0.0.1.dist-info/METADATA
plotnine3d-0.0.1.dist-info/WHEEL
plotnine3d-0.0.1.dist-info/top_level.txt
plotnine3d-0.0.1.dist-info/RECORD
