Metadata-Version: 2.1
Name: plotnine3d
Version: 0.0.1
Summary: 3D geoms for plotnine (grammar of graphics in Python)
Author: Michał Krassowski
License: MIT license
Project-URL: Bug Tracker, https://github.com/krassowski/plotnine3d/issues
Project-URL: Source Code, https://github.com/krassowski/plotnine3d
Classifier: Intended Audience :: Science/Research
Classifier: Intended Audience :: Education
Classifier: License :: OSI Approved :: MIT License
Classifier: Operating System :: Microsoft :: Windows
Classifier: Operating System :: Unix
Classifier: Operating System :: MacOS
Classifier: Programming Language :: Python :: 3 :: Only
Classifier: Programming Language :: Python :: 3.8
Classifier: Programming Language :: Python :: 3.9
Classifier: Programming Language :: Python :: 3.10
Classifier: Framework :: Matplotlib
Classifier: Topic :: Scientific/Engineering :: Visualization
Requires-Python: >=3.9
License-File: LICENSE
Requires-Dist: matplotlib
Requires-Dist: plotnine (>=1.3.0)
